agora_l402/__init__.py
agora_l402/_modidx.py
agora_l402/core.py
agora_l402-0.0.4.dist-info/LICENSE
agora_l402-0.0.4.dist-info/METADATA
agora_l402-0.0.4.dist-info/WHEEL
agora_l402-0.0.4.dist-info/entry_points.txt
agora_l402-0.0.4.dist-info/top_level.txt
agora_l402-0.0.4.dist-info/RECORD
