Metadata-Version: 2.2
Name: agora-l402
Version: 0.0.4
Home-page: https://github.com/Fewsats/agora-l402
Author: Jordi Montes, Pol Alvarez
Author-email: jordi@fewsats.com, pol@fewsats.com
License: Apache Software License 2.0
Keywords: nbdev jupyter notebook python
Classifier: Development Status :: 4 - Beta
Classifier: Intended Audience :: Developers
Classifier: Natural Language :: English
Classifier: Programming Language :: Python :: 3.7
Classifier: Programming Language :: Python :: 3.8
Classifier: Programming Language :: Python :: 3.9
Classifier: Programming Language :: Python :: 3.10
Classifier: Programming Language :: Python :: 3.11
Classifier: Programming Language :: Python :: 3.12
Classifier: License :: OSI Approved :: Apache Software License
Requires-Python: >=3.7
License-File: LICENSE
Requires-Dist: python-fasthtml
Requires-Dist: monsterUI
Requires-Dist: claudette
Requires-Dist: openai-whisper
Requires-Dist: python-dotenv
Requires-Dist: fewsats
Provides-Extra: dev
Requires-Dist: nbdev; extra == "dev"
Requires-Dist: jupyter; extra == "dev"
Dynamic: author
Dynamic: author-email
Dynamic: classifier
Dynamic: description
Dynamic: description-content-type
Dynamic: home-page
Dynamic: keywords
Dynamic: license
Dynamic: provides-extra
Dynamic: requires-dist
Dynamic: requires-python
